{
    "pageTitle" : "Home",
    "pageHeading" : "Welcome to the site",
    "portfolio" : [
        {
            "title" : "Item 1",
            "slug" : "item-1",
            "text" : "Lorem ipsum dolor sit amet, consectetur adipiscing elit. Cras ac elit pellentesque, sollicitudin risus sit amet, bibendum orci. Vivamus auctor arcu sed lectus posuere, ac dignissim lectus semper. Duis ut erat sit amet velit eleifend condimentum. Morbi fermentum est lacinia, efficitur nisi a, tempor arcu. Donec mattis turpis nec velit ullamcorper pulvinar. Cras ullamcorper elementum risus, sed varius nisi.",
            "madewith" : [
                "HTML",
                "CSS",
                "JavaScript/jQuery"
            ]
        },
        {
            "title" : "Item 2",
            "slug" : "item-2",
            "text" : "Lorem ipsum dolor sit amet, consectetur adipiscing elit. Cras ac elit pellentesque, sollicitudin risus sit amet, bibendum orci. Vivamus auctor arcu sed lectus posuere, ac dignissim lectus semper. Duis ut erat sit amet velit eleifend condimentum. Morbi fermentum est lacinia, efficitur nisi a, tempor arcu. Donec mattis turpis nec velit ullamcorper pulvinar. Cras ullamcorper elementum risus, sed varius nisi.",
            "madewith" : [
                "HTML",
                "CSS",
                "JavaScript/jQuery",
                "PHP"
            ]
        }
    ]
}